resfinder-4.7.2.dist-info/METADATA
resfinder-4.7.2.dist-info/WHEEL
resfinder-4.7.2.dist-info/entry_points.txt
resfinder-4.7.2.dist-info/licenses/LICENSE
resfinder/.DS_Store
resfinder/__init__.py
resfinder/__main__.py
resfinder/amr_abbreviations.md
resfinder/cge/.DS_Store
resfinder/cge/__init__.py
resfinder/cge/config.py
resfinder/cge/output/__init__.py
resfinder/cge/output/exceptions.py
resfinder/cge/output/gene_result.py
resfinder/cge/output/orderedset.py
resfinder/cge/output/phenotype_result.py
resfinder/cge/output/seq_variation_result.py
resfinder/cge/output/std_results.py
resfinder/cge/output/table.py
resfinder/cge/phenotype2genotype/__init__.py
resfinder/cge/phenotype2genotype/abclassdef.py
resfinder/cge/phenotype2genotype/dbhit.py
resfinder/cge/phenotype2genotype/feature.py
resfinder/cge/phenotype2genotype/isolate.py
resfinder/cge/phenotype2genotype/phenodbpoint.py
resfinder/cge/phenotype2genotype/phenotype.py
resfinder/cge/phenotype2genotype/res_profile.py
resfinder/cge/phenotype2genotype/res_sumtable.py
resfinder/cge/pointfinder.py
resfinder/cge/resfinder.py
resfinder/cge/runinfo.py
resfinder/environment_variables.md
resfinder/run_resfinder.py
resfinder/species_abbreviations.md
resfinder/species_options.md
resfinder-4.7.2.dist-info/RECORD
