Metadata-Version: 2.1
Name: resfinder
Version: 4.7.2
Summary: ResFinder identifies acquired genes and/or finds chromosomal /
Author-Email: Center for Genomic Epidemiology <food-cgehelp@dtu.dk>
License: Apache-2.0
Requires-Python: >=3.10
Requires-Dist: cgelib>=0.7.3
Requires-Dist: cgecore==2.0.1
Requires-Dist: tabulate>=0.8.9
Requires-Dist: pandas>=1.4.2
Requires-Dist: biopython>=1.79
